cryptokey/__init__.py
cryptokey/hashes.py
cryptokey/math.py
cryptokey/oid.py
cryptokey/py.typed
cryptokey/asn1utils/__init__.py
cryptokey/backend/__init__.py
cryptokey/backend/cryptography/__init__.py
cryptokey/backend/cryptography/hashes.py
cryptokey/backend/cryptography/rsa.py
cryptokey/backend/hashlib/__init__.py
cryptokey/backend/nacl/__init__.py
cryptokey/backend/oscrypto/__init__.py
cryptokey/backend/partial/__init__.py
cryptokey/backend/partial/rsa.py
cryptokey/backend/textbook/__init__.py
cryptokey/backend/textbook/ecc.py
cryptokey/backend/textbook/ecdsa.py
cryptokey/backend/textbook/eddsa.py
cryptokey/backend/textbook/rsa.py
cryptokey/padding/__init__.py
cryptokey/padding/pss.py
cryptokey/padding/v15.py
cryptokey/public/__init__.py
cryptokey/public/dsa.py
cryptokey/public/ecc.py
cryptokey/public/ecdsa.py
cryptokey/public/ed25519.py
cryptokey/public/elgamal.py
cryptokey/public/key.py
cryptokey/public/rsa.py
cryptokey-0.2.2.dist-info/LICENSE
cryptokey-0.2.2.dist-info/METADATA
cryptokey-0.2.2.dist-info/WHEEL
cryptokey-0.2.2.dist-info/top_level.txt
cryptokey-0.2.2.dist-info/zip-safe
cryptokey-0.2.2.dist-info/RECORD
