Metadata-Version: 2.1
Name: cryptokey
Version: 0.2.2
Summary: Python library for pluggable asymmetric low-level encryption
Home-page: https://github.com/joernheissler/cryptokey
Author: Jörn Heissler
Author-email: NOSPAM-cryptokey@joern.heissler.de
License: MIT
Keywords: Cryptography
Platform: UNKNOWN
Classifier: Development Status :: 3 - Alpha
Classifier: Intended Audience :: Developers
Classifier: License :: OSI Approved :: MIT License
Classifier: Programming Language :: Python :: 3
Classifier: Programming Language :: Python :: 3.7
Requires-Python: >= 3.7
Requires-Dist: asn1crypto
